1_RTL/4_COMB_LOGIC/2_ENCODER/interrupt_controller.v
`timescale 1ns / 1ps

module interrupt_controller(
	//port list
	i_int		,// incording interrupt
	i_int_ack	,// cpu ack signal
	o_int_id	,// encordede interrupt id
	o_int_req	 // interrupt id
);

// port declaration
input	[7:0]	i_int		;
input		i_int_ack	;
output	[2:0]	o_int_id	;
output		o_int_req	;

// internal register
reg	[7:0]	r_active_int	;

// modeling
reg	[2:0]	o_int_id	;
reg		o_int_req	;

always @(*)begin
	o_int_id = 3'b000	;
	o_int_req = 1'b0	;
	r_active_int = i_int	;

	if (i_int_ack) begin
		r_active_int = 8'b0000_0000;
	end
	else begin
		casex (r_active_int)
			8'b1xxx_xxxx	: begin o_int_id = 3'b111; o_int_req = 1'b1; end // int7
			8'b01xx_xxxx	: begin o_int_id = 3'b110; o_int_req = 1'b1; end // int6
			8'b001x_xxxx	: begin o_int_id = 3'b101; o_int_req = 1'b1; end // int5
			8'b0001_xxxx	: begin o_int_id = 3'b100; o_int_req = 1'b1; end // int4
			8'b0000_1xxx	: begin o_int_id = 3'b011; o_int_req = 1'b1; end // int3
			8'b0000_01xx	: begin o_int_id = 3'b010; o_int_req = 1'b1; end // int2
			8'b0000_001x	: begin o_int_id = 3'b001; o_int_req = 1'b1; end // int1
			8'b0000_0001	: begin o_int_id = 3'b000; o_int_req = 1'b1; end // int0
			default		: begin o_int_id = 3'b000; o_int_req = 1'b0; end // no requset
		endcase
	end
end

endmodule

1_RTL/4_COMB_LOGIC/2_ENCODER/tb_interrupt_controller.v
`timescale 1ns / 1ps

module tb_interrupt_controller;

//stimulus signal
reg	[7:0]	i_int		;
reg		i_int_ack	;

//monitor signal
wire	[2:0]	o_int_id	;
wire		o_int_req	;

//DUT instantiation
interrupt_controller uut(
	.i_int(i_int),
	.i_int_ack(i_int_ack),
	.o_int_id(o_int_id),
	.o_int_req(o_int_req)
);

//apply stimulus
initial begin
	//monitoring
	$monitor("Time=%0t | i_int=%b | i_int_ack=%b | o_int_id=%b | o_int_req=%b",$time, i_int, i_int_ack, o_int_id, o_int_req);

//init
i_int		= 8'b0000_0000	;
i_int_ack	= 1'b0		;

//apply stimulus
#10 i_int	= 8'b0000_0001	;
#10 i_int	= 8'b0010_0000	;
#10 i_int	= 8'b1000_0000	;
#10 i_int_ack	= 1'b1		;
#10 i_int_ack	= 1'b0		;

#10 i_int	= 8'b0100_0010	;
#10 i_int_ack	= 1'b1		;
#10 i_int_ack	= 1'b0		;

#10 i_int	= 8'b0000_0000	;

#20 $finish;
end

//dumpfile gen
initial begin
	$dumpfile("./interrupt_controller.vcd");
	$dumpvars(0, tb_interrupt_controller);
end

endmodule

1_RTL/4_COMB_LOGIC/2_ENCODER/interrupt_controller.vcd
$date
    Jul  1, 2026  02:13:36
$end
$version
    TOOL:	xmsim(64)	22.03-s012
$end
$timescale
    1 ps
$end

$scope module tb_interrupt_controller $end
$var reg       8 !    i_int [7:0] $end
$var reg       1 "    i_int_ack $end
$var wire      3 #    o_int_id [2:0] $end
$var wire      1 $    o_int_req  $end

$scope module uut $end
$var wire      8 %    i_int [7:0] $end
$var wire      1 &    i_int_ack  $end
$var reg       3 '    o_int_id [2:0] $end
$var reg       1 (    o_int_req $end
$var reg       8 )    r_active_int [7:0] $end
$upscope $end

$upscope $end

$enddefinitions $end
$dumpvars
b0 !
0"
b0 #
0$
b0 %
0&
b0 '
0(
b0 )
$end
#10000
b1 !
b1 %
b1 )
1(
1$
#20000
b100000 !
b100000 %
0(
b100000 )
b101 '
1(
b101 #
#30000
b10000000 !
b10000000 %
b0 '
0(
b10000000 )
b111 '
1(
b111 #
#40000
1"
1&
b0 '
0(
b0 )
0$
b0 #
#50000
0"
0&
b10000000 )
b111 '
1(
1$
b111 #
#60000
b1000010 !
b1000010 %
b0 '
0(
b1000010 )
b110 '
1(
b110 #
#70000
1"
1&
b0 '
0(
b0 )
0$
b0 #
#80000
0"
0&
b1000010 )
b110 '
1(
1$
b110 #
#90000
b0 !
b0 %
b0 '
0(
b0 )
0$
b0 #
